common_utils/__init__.py
common_utils/base_service.py
common_utils/connections.py
common_utils/constants.py
common_utils/datetime.py
common_utils/decorators.py
common_utils/errors.py
common_utils/exceptions.py
common_utils/logger.py
common_utils/message.py
common_utils/microservices.py
common_utils/pagination.py
common_utils/response.py
common_utils/swagger.py
common_utils/utils.py
common_utils/validators.py
platform_users/__init__.py
platform_users/admin.py
platform_users/apps.py
platform_users/errors.py
platform_users/models.py
platform_users/serializers.py
platform_users/services.py
platform_users/tests.py
platform_users/urls.py
platform_users/utils.py
platform_users/views.py
platform_users/migrations/0001_initial.py
platform_users/migrations/__init__.py
platform_users-1.0.7.dist-info/LICENSE
platform_users-1.0.7.dist-info/METADATA
platform_users-1.0.7.dist-info/WHEEL
platform_users-1.0.7.dist-info/top_level.txt
platform_users-1.0.7.dist-info/RECORD
